Metadata-Version: 2.1
Name: flask-oauth2-validation
Version: 0.1.2
Summary: A Flask decorator which adds local and remote OAuth2 validation for self-encoded JWT based Bearer access tokens.
Home-page: https://github.com/0x7d7b/flask-oauth2-validation
Author: Henrik Sachse
Author-email: henrik@0x7d7b.net
License: MIT
Project-URL: Bug Tracker, https://github.com/0x7d7b/flask-oauth2-validation/issues
Project-URL: Source, https://github.com/0x7d7b/flask-oauth2-validation
Project-URL: Test Coverage, https://codecov.io/gh/0x7d7b/flask-oauth2-validation
Classifier: Programming Language :: Python :: 3
Classifier: Framework :: Flask
Classifier: License :: OSI Approved :: MIT License
Classifier: Operating System :: OS Independent
Requires-Python: >=3.9
License-File: LICENSE
